pytrun/__init__.py
pytrun/main.py
pytrun/task_runner.py
pytrun/tests/__init__.py
pytrun/tests/test_task_runner.py
pytrun-1.2.1.dist-info/METADATA
pytrun-1.2.1.dist-info/WHEEL
pytrun-1.2.1.dist-info/entry_points.txt
pytrun-1.2.1.dist-info/top_level.txt
pytrun-1.2.1.dist-info/RECORD
